acme_news/__init__.py
acme_news/browser/__init__.py
acme_news/browser/acme_browser.py
acme_news/database/__init__.py
acme_news/database/acme_db.py
acme_news/engines/__init__.py
acme_news/engines/aljazeera.py
acme_news/engines/cnn.py
acme_news/engines/gman.py
acme_news/engines/google_news.py
acme_news/engines/russia_today.py
acme_news/engines/youtube.py
acme_news/plot/__init__.py
acme_news/plot/graph.py
acme_news/scripts/__init__.py
acme_news/utils/__init__.py
acme_news/utils/constants.py
acme_news/utils/nlp.py
acme_news/utils/tools.py
tests/__init__.py
tests/unit/__init__.py
tests/unit/test_aljazeera_engines.py
tests/unit/test_cnn_engines.py
tests/unit/test_gman_engines.py
tests/unit/test_google_news_engines.py
tests/unit/test_russia_today_engines.py
tests/unit/test_utils.py
tests/unit/test_youtube_engine.py
acmenewscollectors_pkg_rioatmadja2018-0.1.1619577675.dist-info/METADATA
acmenewscollectors_pkg_rioatmadja2018-0.1.1619577675.dist-info/WHEEL
acmenewscollectors_pkg_rioatmadja2018-0.1.1619577675.dist-info/top_level.txt
acmenewscollectors_pkg_rioatmadja2018-0.1.1619577675.dist-info/zip-safe
acmenewscollectors_pkg_rioatmadja2018-0.1.1619577675.dist-info/RECORD
