Metadata-Version: 2.1
Name: acmenewscollectors-pkg-rioatmadja2018
Version: 0.1.1619577675
Summary: Python wheel to collect news articles, videos, and images.
Home-page: UNKNOWN
Author: Rio Atmadja
Author-email: rioatmadja2018@gmail.com
License: UNKNOWN
Platform: UNKNOWN
Classifier: Programming Language :: Python :: 3
Classifier: Operating System :: OS Independent
Classifier: Intended Audience :: Developers
Requires-Python: >=3.6
Requires-Dist: pandas
Requires-Dist: numpy
Requires-Dist: bs4
Requires-Dist: joblib
Requires-Dist: selenium
Requires-Dist: pytest
Requires-Dist: pymysql
Requires-Dist: requests
Requires-Dist: google-api-python-client
Requires-Dist: google-auth-httplib2
Requires-Dist: google-auth-oauthlib
Requires-Dist: nltk
Requires-Dist: matplotlib
Requires-Dist: networkx
Requires-Dist: squarify
Requires-Dist: seaborn
Requires-Dist: google-cloud-language
Requires-Dist: google-cloud-translate (==3.0.1)
